<Properties StartupConfiguration="{05ED22C3-83F0-4C42-81C0-29DE781B74CF}|Default">
  <MonoDevelop.Ide.ItemProperties.Emilia PreferredExecutionTarget="MonoDevelop.Default" />
  <MonoDevelop.Ide.Workbench ActiveDocument="Plugin.cs">
    <Files>
      <File FileName="Program.cs" Line="60" Column="40" />
      <File FileName="Dockerfile" Line="1" Column="1" />
      <File FileName="Plugin.cs" Line="1" Column="1" />
    </Files>
    <Pads>
      <Pad Id="ProjectPad">
        <State name="__root__">
          <Node name="Emilia" expanded="True">
            <Node name="Emilia" expanded="True">
              <Node name="Dependencies" expanded="True" />
              <Node name="Plugin.cs" selected="True" />
            </Node>
          </Node>
        </State>
      </Pad>
    </Pads>
  </MonoDevelop.Ide.Workbench>
  <MonoDevelop.Ide.DebuggingService.PinnedWatches />
  <DisabledProjects>
    <String>docker-compose.dcproj</String>
  </DisabledProjects>
  <MonoDevelop.Ide.Workspace ActiveConfiguration="Debug" />
  <MonoDevelop.Ide.DebuggingService.Breakpoints>
    <BreakpointStore />
  </MonoDevelop.Ide.DebuggingService.Breakpoints>
  <MultiItemStartupConfigurations />
</Properties>